pysonar_scanner/__init__.py
pysonar_scanner/__main__.py
pysonar_scanner/configuration.py
pysonar_scanner/environment.py
pysonar_scanner/logger.py
pysonar_scanner/scanner.py
pysonar_scanner/utils/__init__.py
pysonar_scanner/utils/binaries_utils.py
pysonar_scanner-0.3.0.2016.dist-info/LICENSE
pysonar_scanner-0.3.0.2016.dist-info/METADATA
pysonar_scanner-0.3.0.2016.dist-info/WHEEL
pysonar_scanner-0.3.0.2016.dist-info/entry_points.txt
pysonar_scanner-0.3.0.2016.dist-info/RECORD
